tests/__init__.py
tests/test_cem.py
tests/test_dcr.py
tests/test_logic_layer.py
tests/test_utils.py
torch_explain/__init__.py
torch_explain/_version.py
torch_explain/datasets/__init__.py
torch_explain/datasets/benchmarks.py
torch_explain/logic/__init__.py
torch_explain/logic/metrics.py
torch_explain/logic/utils.py
torch_explain/logic/nn/__init__.py
torch_explain/logic/nn/entropy.py
torch_explain/logic/nn/psi.py
torch_explain/logic/nn/utils.py
torch_explain/nn/__init__.py
torch_explain/nn/concepts.py
torch_explain/nn/logic.py
torch_explain/nn/semantics.py
torch_explain/nn/functional/__init__.py
torch_explain/nn/functional/loss.py
torch_explain/nn/functional/prune.py
torch_explain-1.5.1.dist-info/LICENSE
torch_explain-1.5.1.dist-info/METADATA
torch_explain-1.5.1.dist-info/WHEEL
torch_explain-1.5.1.dist-info/top_level.txt
torch_explain-1.5.1.dist-info/RECORD
